convex-0.7.0.dist-info/METADATA
convex-0.7.0.dist-info/WHEEL
convex-0.7.0.dist-info/licenses/LICENSE
_convex.libs/libgcc_s-b5472b99.so.1
_convex/_convex.pyi
_convex/__init__.py
_convex/int64.py
_convex/py.typed
convex/values.py
convex/http_client.py
convex/__init__.py
convex/py.typed
_convex/_convex.abi3.so
convex-0.7.0.dist-info/RECORD
