Metadata-Version: 2.4
Name: convex
Version: 0.7.0
Classifier: Development Status :: 3 - Alpha
Classifier: Programming Language :: JavaScript
Classifier: Programming Language :: Python :: Implementation :: CPython
Classifier: Programming Language :: Rust
Classifier: Topic :: Database :: Front-Ends
Classifier: Topic :: Software Development :: Libraries :: Python Modules
License-File: LICENSE
Summary: Python client for the reactive backend-as-a-service Convex.
Author-email: "Convex, Inc" <support@convex.dev>
License: Apache-2.0
Requires-Python: >=3.9
Project-URL: homepage, https://convex.dev
Project-URL: repository, https://github.com/get-convex/convex-py
Project-URL: documentation, https://docs.convex.dev
